pandastabletooltip/__init__.py
pandastabletooltip/main.py
tests/__init__.py
tests/test_main.py
pandastabletooltip-0.0.1.dist-info/LICENSE
pandastabletooltip-0.0.1.dist-info/METADATA
pandastabletooltip-0.0.1.dist-info/WHEEL
pandastabletooltip-0.0.1.dist-info/top_level.txt
pandastabletooltip-0.0.1.dist-info/RECORD
