Metadata-Version: 2.1
Name: pandastabletooltip
Version: 0.0.1
Summary: Pandas Table Tooltip is a Python librarythat only adds tooltips to Pandas tables on Jupyter.
Home-page: https://github.com/simon-ritchie/pandas-table-tooltip
Author: simon-ritchie
Author-email: 
Maintainer: simon-ritchie
Maintainer-email: 
License: MIT
Platform: UNKNOWN
Classifier: Programming Language :: Python :: 2
Classifier: Programming Language :: Python :: 2.7
Classifier: Programming Language :: Python :: 3
Classifier: License :: OSI Approved :: MIT License
